G_Sketch/__init__.py
G_Sketch/classes.py
tests/__init__.py
tests/tests.py
G_Sketch-0.1.4.dist-info/METADATA
G_Sketch-0.1.4.dist-info/WHEEL
G_Sketch-0.1.4.dist-info/top_level.txt
G_Sketch-0.1.4.dist-info/RECORD
