Metadata-Version: 2.1
Name: G-Sketch
Version: 0.1.4
Summary: Converts image files to coordinates
Home-page: UNKNOWN
Author: Gerald Negvesky
License: Free use
Platform: UNKNOWN
Requires-Dist: Pillow
